zsdstools/__init__.py
zsdstools/dstools.py
zsdstools-0.2.4.dist-info/LICENSE
zsdstools-0.2.4.dist-info/METADATA
zsdstools-0.2.4.dist-info/WHEEL
zsdstools-0.2.4.dist-info/top_level.txt
zsdstools-0.2.4.dist-info/RECORD
