Metadata-Version: 2.1
Name: zsdstools
Version: 0.2.4
Summary: For quickly create statistics analysis tools on Machine Learning models
Home-page: https://github.com/EasonJia9598/zsdstool
Author: Eason Jia
Author-email: will.jia.sheng@gmail.com
License: UNKNOWN
Platform: UNKNOWN
Classifier: Programming Language :: Python :: 3
Classifier: License :: OSI Approved :: MIT License
Classifier: Operating System :: OS Independent
Requires-Python: >=3.7
License-File: LICENSE
